gnip_trend_detection/__init__.py
gnip_trend_detection/analysis.py
gnip_trend_detection/library.py
gnip_trend_detection/mk_test.py
gnip_trend_detection/models.py
gnip_trend_detection/rebin.py
gnip_trend_detection/time_bucket.py
gnip_trend_detection/utils.py
gnip_trend_detection-0.6.data/scripts/time_series_correlations.py
gnip_trend_detection-0.6.data/scripts/trend_analyze.py
gnip_trend_detection-0.6.data/scripts/trend_analyze_many.py
gnip_trend_detection-0.6.data/scripts/trend_detector.py
gnip_trend_detection-0.6.data/scripts/trend_plot.py
gnip_trend_detection-0.6.data/scripts/trend_rebin.py
gnip_trend_detection-0.6.dist-info/DESCRIPTION.rst
gnip_trend_detection-0.6.dist-info/METADATA
gnip_trend_detection-0.6.dist-info/RECORD
gnip_trend_detection-0.6.dist-info/WHEEL
gnip_trend_detection-0.6.dist-info/metadata.json
gnip_trend_detection-0.6.dist-info/top_level.txt
