Metadata-Version: 2.0
Name: gnip-trend-detection
Version: 0.6
Summary: Trend/spike detection on time series from Twitter
Home-page: https://github.com/tw-ddis/Gnip-Trend-Detection
Author: Jeff Kolb
Author-email: jeffakolb@gmail.com
License: MIT
Platform: UNKNOWN
Requires-Dist: scipy
Requires-Dist: sklearn
Requires-Dist: datetime-truncate
Requires-Dist: python-dateutil
Requires-Dist: matplotlib
